myriadsocial/__init__.py
myriadsocial/cli.py
myriadsocial/myriad-cli.py
myriadsocial-0.1.0.dist-info/METADATA
myriadsocial-0.1.0.dist-info/WHEEL
myriadsocial-0.1.0.dist-info/entry_points.txt
myriadsocial-0.1.0.dist-info/top_level.txt
myriadsocial-0.1.0.dist-info/RECORD
